[{
  "did":44632,
  "personalInfo":{
    "fname":"Saqlain",
    "lname":"Mushtaq",
    "address":{
      "street":"str#7,near anarkali",
      "city":"lahore",
      "district":"lahore",
      "division":"lahore",
      "province":"punjab"
    },
    "dob":"7-11-1970",
    "gender":"male",
    "religion":"islam",
    "profession":"banker"
  },
  "familyNumber":[
    {"current":"23456"},
    {"previous":""}
    ],
  "relations":{
    "father":"Mushtaq",
    "mother":"Ayesha"
  }
},
{
  "did":43689,
  "personalInfo":{
    "fname":"Amina",
    "lname":"Riaz",
    "address":{
      "street":"str#7,near anarkali",
      "city":"lahore",
      "district":"lahore",
      "division":"lahore",
      "province":"punjab"
    },
    "dob":"3-5-1971",
    "gender":"female",
    "religion":"islam",
    "profession":""
  },
  "familyNumber":[
    {"current":"23456"},
    {"previous":"23789"}
    ],
  "relations":{
    "father":"Riaz",
    "mother":"Maryam"
  }
},
{
  "did":45125,
  "personalInfo":{
    "fname":"Ali",
    "lname":"Saqlain",
    "address":{
      "street":"str#7,near anarkali",
      "city":"lahore",
      "district":"lahore",
      "division":"lahore",
      "province":"punjab"
    },
    "dob":"7-11-1995",
    "gender":"male",
    "religion":"islam",
    "profession":"Doctor"
  },
  "familyNumber":[
    {"current":"23567"},
    {"previous":"23456"}
    ],
  "relations":{
    "father":"Saqlain",
    "mother":"Amina"
  }
},
{
  "did":45326,
  "personalInfo":{
    "fname":"Hamza",
    "lname":"Saqlain",
    "address":{
      "street":"str#7,near anarkali",
      "city":"lahore",
      "district":"lahore",
      "division":"lahore",
      "province":"punjab"
    },
    "dob":"2-3-1998",
    "gender":"male",
    "religion":"islam",
    "profession":"student"
  },
  "familyNumber":[
    {"current":"23456"},
    {"previous":""}
    ],
  "relations":{
   "father":"Saqlain",
    "mother":"Amina"
  }
},

{
  "did":45965,
  "personalInfo":{
    "fname":"Mahnoor",
    "lname":"Fatima",
    "address":{
      "street":"str#7,near anarkali",
      "city":"lahore",
      "district":"lahore",
      "division":"lahore",
      "province":"punjab"
    },
    "dob":"2-3-2001",
    "gender":"female",
    "religion":"islam",
    "profession":"student"
  },
  "familyNumber":[
    {"current":"23456"},
    {"previous":""}
    ],
  "relations":{
   "father":"Saqlain",
    "mother":"Amina"
  }
}
]


